Templer-1.1.4.dist-info/METADATA
Templer-1.1.4.dist-info/RECORD
Templer-1.1.4.dist-info/WHEEL
Templer-1.1.4.dist-info/entry_points.txt
Templer-1.1.4.dist-info/top_level.txt
templer/__init__.py
templer/__main__.py
templer/cli.py
templer/jinja_filter.py
