Metadata-Version: 2.1
Name: Templer
Version: 1.1.4
Summary: Render template files with the power of Jinja2.
Home-page: https://github.com/Aisbergg/python-templer
Author: Andre Lehmann
Author-email: aisberg@posteo.de
License: LGPL
Project-URL: Bug Reports, https://github.com/Aisbergg/python-templer/issues
Project-URL: Source, https://github.com/Aisbergg/python-templer
Keywords: Jinja2 templating command-line CLI
Platform: POSIX
Classifier: Development Status :: 4 - Beta
Classifier: Environment :: Console
Classifier: Intended Audience :: Developers
Classifier: Intended Audience :: System Administrators
Classifier: License :: OSI Approved :: GNU Lesser General Public License v3 (LGPLv3)
Classifier: Operating System :: POSIX
Classifier: Programming Language :: Python :: 3 :: Only
Classifier: Topic :: System :: Systems Administration
Classifier: Topic :: Utilities
Requires-Dist: jinja2
Requires-Dist: pyyaml
